linkedin_matrix/__init__.py
linkedin_matrix/__main__.py
linkedin_matrix/commands/__init__.py
linkedin_matrix/commands/auth.py
linkedin_matrix/commands/typehint.py
linkedin_matrix/config.py
linkedin_matrix/db/__init__.py
linkedin_matrix/db/message.py
linkedin_matrix/db/model_base.py
linkedin_matrix/db/portal.py
linkedin_matrix/db/puppet.py
linkedin_matrix/db/reaction.py
linkedin_matrix/db/upgrade/__init__.py
linkedin_matrix/db/upgrade/v01_initial_revision.py
linkedin_matrix/db/upgrade/v02_multiple_reaction_per_message.py
linkedin_matrix/db/upgrade/v03_add_topic_to_portal.py
linkedin_matrix/db/upgrade/v04_add_portal_meta_set.py
linkedin_matrix/db/upgrade/v05_add_index_to_reaction.py
linkedin_matrix/db/user.py
linkedin_matrix/db/user_portal.py
linkedin_matrix/example-config.yaml
linkedin_matrix/formatter/__init__.py
linkedin_matrix/formatter/from_linkedin.py
linkedin_matrix/formatter/from_matrix.py
linkedin_matrix/get_version.py
linkedin_matrix/matrix.py
linkedin_matrix/portal.py
linkedin_matrix/puppet.py
linkedin_matrix/user.py
linkedin_matrix/version.py
linkedin_matrix/web/__init__.py
linkedin_matrix/web/provisioning_api.py
linkedin_matrix-0.5.3.dist-info/LICENSE
linkedin_matrix-0.5.3.dist-info/WHEEL
linkedin_matrix-0.5.3.dist-info/METADATA
linkedin_matrix-0.5.3.dist-info/RECORD
