Metadata-Version: 2.1
Name: linkedin-matrix
Version: 0.5.3
Summary: A Matrix-LinkedIn Messages puppeting bridge.
Home-page: https://github.com/beeper/linkedin
License: Apache-2.0
Keywords: matrix,LinkedIn
Author: Sumner Evans
Author-email: inquiries@sumnerevans.com
Requires-Python: >=3.9,<4.0
Classifier: Development Status :: 3 - Alpha
Classifier: License :: OSI Approved :: Apache Software License
Classifier: Programming Language :: Python :: 3
Classifier: Programming Language :: Python :: 3.10
Classifier: Programming Language :: Python :: 3.9
Classifier: Topic :: Communications :: Chat
Provides-Extra: e2be
Provides-Extra: images
Provides-Extra: metrics
Requires-Dist: Pillow (>=8.3.1,<9.0.0); extra == "images"
Requires-Dist: asyncpg (>=0.23.0)
Requires-Dist: commonmark (>=0.9.1,<0.10.0)
Requires-Dist: linkedin-messaging (>=0.5.2,<0.6.0)
Requires-Dist: mautrix (>=0.17.6,<0.18.0)
Requires-Dist: prometheus-client (>=0.11.0,<0.12.0); extra == "metrics"
Requires-Dist: pycryptodome (>=3.10.1,<4.0.0); extra == "e2be"
Requires-Dist: python-magic (>=0.4.24,<0.5.0)
Requires-Dist: python-olm; extra == "e2be"
Requires-Dist: ruamel.yaml (>=0.17.0,<0.18.0)
Requires-Dist: unpaddedbase64 (>=2.1.0,<3.0.0); extra == "e2be"
Project-URL: Repository, https://github.com/beeper/linkedin
